embci/__init__.py
embci/classifier.py
embci/configs.py
embci/constants.py
embci/io.py
embci/apps/__init__.py
embci/apps/__main__.py
embci/apps/DBS/__init__.py
embci/apps/DBS/__main__.py
embci/apps/DBS/utils.py
embci/apps/SPIScreen/__init__.py
embci/apps/SPIScreen/__main__.py
embci/apps/StreamInfo/__init__.py
embci/apps/StreamInfo/__main__.py
embci/apps/TGAM/__init__.py
embci/apps/WiFi/__init__.py
embci/apps/example/__init__.py
embci/apps/example/__main__.py
embci/apps/example/test.py
embci/apps/sEMG/__init__.py
embci/apps/sEMG/__main__.py
embci/gyms/__init__.py
embci/gyms/gym_torcs.py
embci/gyms/plane_client.py
embci/gyms/snakeoil3_gym.py
embci/processing/__init__.py
embci/processing/freqd.py
embci/processing/motorimagery.py
embci/processing/p300.py
embci/processing/preprocess.py
embci/processing/ssvep.py
embci/processing/timed.py
embci/utils/__init__.py
embci/utils/ads1299_api.py
embci/utils/argparse.py
embci/utils/esp32_api.py
embci/utils/ili9341_api.py
embci/viz/__init__.py
embci/viz/plots.py
embci/viz/qt.py
embci/viz/screen.py
embci/webui/__init__.py
embci/webui/__main__.py
EmBCI-0.1.2.dist-info/LICENSE.txt
EmBCI-0.1.2.dist-info/METADATA
EmBCI-0.1.2.dist-info/WHEEL
EmBCI-0.1.2.dist-info/entry_points.txt
EmBCI-0.1.2.dist-info/top_level.txt
EmBCI-0.1.2.dist-info/RECORD
