Metadata-Version: 2.1
Name: EmBCI
Version: 0.1.2
Summary: 
Requires-Dist: bottle
Requires-Dist: gevent-websocket
Requires-Dist: bottle-websocket
Requires-Dist: gevent
Requires-Dist: wifi
Requires-Dist: pyserial
Requires-Dist: gpio4
Requires-Dist: spidev
Requires-Dist: keras
Requires-Dist: sklearn
Requires-Dist: pillow
Requires-Dist: decorator
Requires-Dist: dill
Requires-Dist: six
Requires-Dist: pyhht
Requires-Dist: pywavelets
Requires-Dist: pylsl
Requires-Dist: scipy
Requires-Dist: numpy
Requires-Dist: mne
Provides-Extra: rest
Requires-Dist: docutils (>=0.3) ; extra == 'rest'
